[
  {
    "start":"上海",
    "wrhouse":[
      {
        "houseName":"上海仓库",
        "times":[
          {
            "meetingDate":"上海-上海仓库的集货交期",
            "finishDate":"上海-上海仓库的目的港交期",
            "resvDate":"上海-上海仓库的预约日期",
            "resvTime":"上海-上海仓库的预约时段"
          }
        ]
      },
      {
        "houseName":"大洋仓库",
        "times":[
          {
            "meetingDate":"上海-大洋仓库的集货交期",
            "finishDate":"上海-大洋仓库的目的港交期",
            "resvDate":"上海-大洋仓库的预约日期",
            "resvTime":"上海-大洋仓库的预约时段"
          }
        ]
      },
      {
        "houseName":"南通仓库",
        "times":[
          {
            "meetingDate":"上海-南通仓库的集货交期",
            "finishDate":"上海-南通仓库的目的港交期",
            "resvDate":"上海-南通仓库的预约日期",
            "resvTime":"上海-南通仓库的预约时段"
          }
        ]
      },
      {
        "houseName":"迪士尼仓库",
        "times":[
          {
            "meetingDate":"上海-迪士尼仓库的集货交期",
            "finishDate":"上海-迪士尼仓库的目的港交期",
            "resvDate":"上海-迪士尼仓库的预约日期",
            "resvTime":"上海-迪士尼仓库的预约时段"
          }
        ]
      }

    ]
  },
  {
    "start":"宁波",
    "wrhouse":[
      {
        "houseName":"宁波仓库",
        "times":[
          {
            "meetingDate":"2017-06-05",
            "finishDate":"2017-05-12",
            "resvDate":"2017-05-12",
            "resvTime":"09:00-10:00"
          }
        ]
      },
      {
        "houseName":"大洋仓库",
        "times":[
          {
            "meetingDate":"2017-06-05",
            "finishDate":"2017-05-12",
            "resvDate":"2017-05-12",
            "resvTime":"09:00-10:00"
          }
        ]
      },
      {
        "houseName":"浙江仓库",
        "times":[
          {
            "meetingDate":"2017-06-05",
            "finishDate":"2017-05-12",
            "resvDate":"2017-05-12",
            "resvTime":"09:00-10:00"
          }
        ]
      },
      {
        "houseName":"集合仓库",
        "times":[
          {
            "meetingDate":"2017-06-05",
            "finishDate":"2017-05-12",
            "resvDate":"2017-05-12",
            "resvTime":"09:00-10:00"
          }
        ]
      }

    ]
  },
  {
    "start":"深圳",
    "wrhouse":[
      {
        "houseName":"深圳仓库",
        "times":[
          {
            "meetingDate":"2017-06-05",
            "finishDate":"2017-05-12",
            "resvDate":"2017-05-12",
            "resvTime":"09:00-10:00"
          }
        ]
      },
      {
        "houseName":"大洋仓库",
        "times":[
          {
            "meetingDate":"2017-06-05",
            "finishDate":"2017-05-12",
            "resvDate":"2017-05-12",
            "resvTime":"09:00-10:00"
          }
        ]
      },
      {
        "houseName":"南通仓库",
        "times":[
          {
            "meetingDate":"2017-06-05",
            "finishDate":"2017-05-12",
            "resvDate":"2017-05-12",
            "resvTime":"09:00-10:00"
          }
        ]
      },
      {
        "houseName":"迪士尼仓库",
        "times":[
          {
            "meetingDate":"2017-06-05",
            "finishDate":"2017-05-12",
            "resvDate":"2017-05-12",
            "resvTime":"09:00-10:00"
          }
        ]
      }

    ]
  },
  {
    "start":"北京",
    "wrhouse":[
      {
        "houseName":"北京仓库",
        "times":[
          {
            "meetingDate":"2017-06-05",
            "finishDate":"2017-05-12",
            "resvDate":"2017-05-12",
            "resvTime":"09:00-10:00"
          }
        ]
      },
      {
        "houseName":"大洋仓库",
        "times":[
          {
            "meetingDate":"2017-06-05",
            "finishDate":"2017-05-12",
            "resvDate":"2017-05-12",
            "resvTime":"09:00-10:00"
          }
        ]
      },
      {
        "houseName":"南通仓库",
        "times":[
          {
            "meetingDate":"2017-06-05",
            "finishDate":"2017-05-12",
            "resvDate":"2017-05-12",
            "resvTime":"09:00-10:00"
          }
        ]
      },
      {
        "houseName":"迪士尼仓库",
        "times":[
          {
            "meetingDate":"2017-06-05",
            "finishDate":"2017-05-12",
            "resvDate":"2017-05-12",
            "resvTime":"09:00-10:00"
          }
        ]
      }

    ]
  },
  {
    "start":"广东",
    "wrhouse":[
      {
        "houseName":"广东仓库",
        "times":[
          {
            "meetingDate":"2017-06-05",
            "finishDate":"2017-05-12",
            "resvDate":"2017-05-12",
            "resvTime":"09:00-10:00"
          }
        ]
      },
      {
        "houseName":"大洋仓库",
        "times":[
          {
            "meetingDate":"2017-06-05",
            "finishDate":"2017-05-12",
            "resvDate":"2017-05-12",
            "resvTime":"09:00-10:00"
          }
        ]
      },
      {
        "houseName":"南通仓库",
        "times":[
          {
            "meetingDate":"2017-06-05",
            "finishDate":"2017-05-12",
            "resvDate":"2017-05-12",
            "resvTime":"09:00-10:00"
          }
        ]
      },
      {
        "houseName":"迪士尼仓库",
        "times":[
          {
            "meetingDate":"2017-06-05",
            "finishDate":"2017-05-12",
            "resvDate":"2017-05-12",
            "resvTime":"09:00-10:00"
          }
        ]
      }

    ]
  },
  {
    "start":"天津",
    "wrhouse":[
      {
        "houseName":"天津仓库",
        "times":[
          {
            "meetingDate":"2017-06-05",
            "finishDate":"2017-05-12",
            "resvDate":"2017-05-12",
            "resvTime":"09:00-10:00"
          }
        ]
      },
      {
        "houseName":"大洋仓库",
        "times":[
          {
            "meetingDate":"2017-06-05",
            "finishDate":"2017-05-12",
            "resvDate":"2017-05-12",
            "resvTime":"09:00-10:00"
          }
        ]
      },
      {
        "houseName":"南通仓库",
        "times":[
          {
            "meetingDate":"2017-06-05",
            "finishDate":"2017-05-12",
            "resvDate":"2017-05-12",
            "resvTime":"09:00-10:00"
          }
        ]
      },
      {
        "houseName":"迪士尼仓库",
        "times":[
          {
            "meetingDate":"2017-06-05",
            "finishDate":"2017-05-12",
            "resvDate":"2017-05-12",
            "resvTime":"09:00-10:00"
          }
        ]
      }

    ]
  },
  {
    "start":"厦门",
    "wrhouse":[
      {
        "houseName":"厦门仓库",
        "times":[
          {
            "meetingDate":"2017-06-05",
            "finishDate":"2017-05-12",
            "resvDate":"2017-05-12",
            "resvTime":"09:00-10:00"
          }
        ]
      },
      {
        "houseName":"大洋仓库",
        "times":[
          {
            "meetingDate":"2017-06-05",
            "finishDate":"2017-05-12",
            "resvDate":"2017-05-12",
            "resvTime":"09:00-10:00"
          }
        ]
      },
      {
        "houseName":"南通仓库",
        "times":[
          {
            "meetingDate":"2017-06-05",
            "finishDate":"2017-05-12",
            "resvDate":"2017-05-12",
            "resvTime":"09:00-10:00"
          }
        ]
      },
      {
        "houseName":"迪士尼仓库",
        "times":[
          {
            "meetingDate":"2017-06-05",
            "finishDate":"2017-05-12",
            "resvDate":"2017-05-12",
            "resvTime":"09:00-10:00"
          }
        ]
      }

    ]
  }

]